Workbook

Sheet Instructions
A1: Couples Shared Budget Spreadsheet – Google Sheets Tracker for Bills, Expenses & Savings (7 USD)
A3: 1. Make a copy of the Google Sheet to your own Google Drive (File → Make a copy).
A4: 2. Enter your joint accounts in the Overview tab and link them to the Income and Expenses tabs.
A5: 3. Record all income entries in the Income tab and every bill or purchase in the Expenses tab, selecting who paid it and setting a due date if applicable.
A6: 4. Review the Overview tab regularly to see current balances, total income, total expenses, and net balance.
A8: Works in Microsoft Excel, Google Sheets (File > Import) and Apple Numbers.
A10: Blue header rows stay visible while you scroll. Totals sit under each table.
A11: This template helps you organise your own numbers. It is not financial, tax or legal advice.

Sheet Dashboard
A1: Summary | B1: Value
A2: Overview: Current Balance | B2: ='Overview'!B6
A3: Overview: Total Income | B3: ='Overview'!C6
A4: Overview: Total Expenses | B4: ='Overview'!D6
A5: Overview: Net Balance | B5: ='Overview'!E6
A6: Income: Amount | B6: ='Income'!C7
A7: Expenses: Amount | B7: ='Expenses'!D7
A8: Expenses: Overdue rows | B8: ='Expenses'!B8

Sheet Overview
A1: Account Name | B1: Current Balance | C1: Total Income | D1: Total Expenses | E1: Net Balance
A2: Checking | B2: 2150 | C2: 4200 | D2: 2050 | E2: 1150
A3: Savings | B3: 5300 | C3: 1500 | D3: 200 | E3: 6600
A4: Credit Card | B4: -350 | C4: 0 | D4: 350 | E4: -700
A6: TOTAL | B6: =SUM(B2:B4) | C6: =SUM(C2:C4) | D6: =SUM(D2:D4) | E6: =SUM(E2:E4)

Sheet Income
A1: Date | B1: Source | C1: Amount | D1: Notes | E1: Balance
A2: 46054 | B2: Partner A Salary | C2: 2600 | D2: Monthly paycheck | E2: =N(C2)-0
A3: 46056 | B3: Partner B Freelance | C3: 800 | D3: Design project | E3: =N(E2)+N(C3)-0
A4: 46068 | B4: Gift from family | C4: 250 | D4: Birthday | E4: =N(E3)+N(C4)-0
A5: 46073 | B5: Interest | C5: 15 | D5: Savings account | E5: =N(E4)+N(C5)-0
A7: TOTAL | C7: =SUM(C2:C5)

Sheet Expenses
A1: Date | B1: Category | C1: Sub‑category | D1: Amount | E1: Paid By | F1: Due Date | G1: Status | H1: Balance | I1: Overdue?
A2: 46058 | B2: Rent | C2: Apartment | D2: 1200 | E2: Both | F2: 46058 | G2: Paid | H2: =0-N(D2) | I2: =IF(AND(ISNUMBER(F2),G2<>"Paid",F2<TODAY()),"OVERDUE","")
A3: 46063 | B3: Utilities | C3: Electricity | D3: 90 | E3: Partner A | F3: 46068 | G3: Unpaid | H3: =N(H2)+0-N(D3) | I3: =IF(AND(ISNUMBER(F3),G3<>"Paid",F3<TODAY()),"OVERDUE","")
A4: 46065 | B4: Food | C4: Groceries | D4: 180 | E4: Partner B | F4: 46065 | G4: Paid | H4: =N(H3)+0-N(D4) | I4: =IF(AND(ISNUMBER(F4),G4<>"Paid",F4<TODAY()),"OVERDUE","")
A5: 46071 | B5: Entertainment | C5: Streaming | D5: 15 | E5: Both | F5: 46071 | G5: Paid | H5: =N(H4)+0-N(D5) | I5: =IF(AND(ISNUMBER(F5),G5<>"Paid",F5<TODAY()),"OVERDUE","")
A7: TOTAL | D7: =SUM(D2:D5)
A8: Overdue rows | B8: =COUNTIF(I2:I5,"OVERDUE")
