Workbook

Sheet Instructions
A1: College Textbook Expense Tracker – Google Sheets Template for Students
A3: 1. Add the product to your cart on Gumroad and click the “Get Google Sheets Template” button.
A4: 2. A copy of the file opens in your Google Drive – use File → Make a copy to save it to your own folder.
A5: 3. In the Overview tab, enter your semester name and the total amount you plan to spend on textbooks.
A6: 4. Fill in the Semester Planner with each course’s code, title, and start/end dates; the “Days Until Start” column updates automatically.
A7: 5. Open the Textbook List tab and add every required book, completing price fields and marking “Purchased?” when you buy a book. Totals update across the file instantly.
A8: 6. Check the Reports tab for visual charts that show where your money is going and whether you’re staying under budget.
A10: Works in Microsoft Excel, Google Sheets (File > Import) and Apple Numbers.
A12: Blue header rows stay visible while you scroll. Totals sit under each table.
A13: This template helps you organise your own numbers. It is not financial, tax or legal advice.

Sheet Dashboard
A1: Summary | B1: Value
A2: Overview: Total Budget | B2: ='Overview'!B6
A3: Overview: Total Spent | B3: ='Overview'!C6
A4: Overview: Remaining Balance | B4: ='Overview'!D6
A5: Overview: Percent Used | B5: ='Overview'!E6
A6: Textbook List: List Price | B6: ='Textbook List'!D6
A7: Textbook List: Discounted Price | B7: ='Textbook List'!E6
A8: Textbook List: Final Price | B8: ='Textbook List'!F6
A9: Expense Ledger: In Amount | B9: ='Expense Ledger'!C7
A10: Expense Ledger: Out Amount | B10: ='Expense Ledger'!D7

Sheet Overview
A1: Semester | B1: Total Budget | C1: Total Spent | D1: Remaining Balance | E1: Percent Used
A2: Fall 2025 | B2: 500 | C2: 320 | D2: 180 | E2: 64
A3: Spring 2026 | B3: 450 | C3: 150 | D3: 300 | E3: 33.33
A4: Summer 2026 | B4: 300 | C4: 0 | D4: 300 | E4: 0
A6: TOTAL | B6: =SUM(B2:B4) | C6: =SUM(C2:C4) | D6: =SUM(D2:D4) | E6: =SUM(E2:E4)

Sheet Textbook List
A1: Course | B1: Textbook Title | C1: Store | D1: List Price | E1: Discounted Price | F1: Final Price | G1: Purchased? | H1: Date Purchased
A2: ENG101 | B2: Introduction to Literature | C2: Campus Bookstore | D2: 120 | E2: 100 | F2: 100 | G2: Yes | H2: 46249
A3: MATH201 | B3: Calculus II | C3: Amazon | D3: 200 | E3: 150 | F3: 150 | G3: No
A4: HIST150 | B4: World History | C4: eCampus | D4: 80 | E4: 80 | F4: 80 | G4: Yes | H4: 46254
A6: TOTAL | D6: =SUM(D2:D4) | E6: =SUM(E2:E4) | F6: =SUM(F2:F4)

Sheet Expense Ledger
A1: Date | B1: Description | C1: In Amount | D1: Out Amount | E1: Balance
A2: 46235 | B2: Scholarship received | C2: 500 | D2: 0 | E2: =N(C2)-N(D2)
A3: 46244 | B3: Textbook purchase - ENG101 | C3: 0 | D3: 100 | E3: =N(E2)+N(C3)-N(D3)
A4: 46246 | B4: Textbook purchase - MATH201 | C4: 0 | D4: 150 | E4: =N(E3)+N(C4)-N(D4)
A5: 46254 | B5: Returned book refund | C5: 20 | D5: 0 | E5: =N(E4)+N(C5)-N(D5)
A7: TOTAL | C7: =SUM(C2:C5) | D7: =SUM(D2:D5)
