Workbook

Sheet Instructions
A1: Etsy Profit Calculator – Google Sheet for Handmade Sellers (Fees, Shipping, Net Profit)
A3: 1. Open the Google Sheet and go to the Settings tab; select your shop type (Etsy, Amazon Handmade, etc.) and set your default currency and shipping rate.
A4: 2. The Fees tab will auto‑populate the correct listing, transaction, and payment fee rates based on the shop type you chose.
A5: 3. Enter each product in the Profit tab: SKU, Units Sold, Unit Price, and Shipping Cost. The sheet will calculate all fees and show Net Profit per line item.
A6: 4. Use the Payments tab to log invoices, mark them Paid or Unpaid, and see which ones are overdue.
A7: 5. Check the Dashboard tab for a summarized view of total profit, average margin, and progress toward any profit goal you set.
A9: Works in Microsoft Excel, Google Sheets (File > Import) and Apple Numbers.
A11: Blue header rows stay visible while you scroll. Totals sit under each table.
A12: This template helps you organise your own numbers. It is not financial, tax or legal advice.

Sheet Dashboard
A1: Summary | B1: Value
A2: Profit: Units Sold | B2: ='Profit'!B7
A3: Profit: Unit Price | B3: ='Profit'!C7
A4: Profit: Listing Fee | B4: ='Profit'!D7
A5: Profit: Transaction Fee | B5: ='Profit'!E7
A6: Profit: Payment Fee | B6: ='Profit'!F7
A7: Profit: Shipping Cost | B7: ='Profit'!G7
A8: Profit: Total Cost | B8: ='Profit'!H7
A9: Profit: Net Profit | B9: ='Profit'!I7
A10: Fees: Listing Fee | B10: ='Fees'!B6
A11: Fees: Transaction Fee | B11: ='Fees'!C6
A12: Fees: Payment Fee | B12: ='Fees'!D6
A13: Payments: Amount | B13: ='Payments'!C7
A14: Payments: Overdue rows | B14: ='Payments'!B8

Sheet Profit
A1: Item | B1: Units Sold | C1: Unit Price | D1: Listing Fee | E1: Transaction Fee | F1: Payment Fee | G1: Shipping Cost | H1: Total Cost | I1: Net Profit | J1: Balance
A2: Handmade Necklace | B2: 30 | C2: 25 | D2: 0.2 | E2: 1.25 | F2: 0.75 | G2: 3 | H2: 5.2 | I2: 19.8 | J2: =N(I2)-0
A3: Soy Candle | B3: 50 | C3: 12 | D3: 0.2 | E3: 0.6 | F3: 0.36 | G3: 2 | H3: 3.16 | I3: 8.84 | J3: =N(J2)+N(I3)-0
A4: Knitted Scarf | B4: 20 | C4: 35 | D4: 0.2 | E4: 1.75 | F4: 1.05 | G4: 4 | H4: 7 | I4: 28 | J4: =N(J3)+N(I4)-0
A5: Ceramic Mug | B5: 40 | C5: 18 | D5: 0.2 | E5: 0.9 | F5: 0.54 | G5: 2.5 | H5: 4.14 | I5: 13.86 | J5: =N(J4)+N(I5)-0
A7: TOTAL | B7: =SUM(B2:B5) | C7: =SUM(C2:C5) | D7: =SUM(D2:D5) | E7: =SUM(E2:E5) | F7: =SUM(F2:F5) | G7: =SUM(G2:G5) | H7: =SUM(H2:H5) | I7: =SUM(I2:I5)

Sheet Fees
A1: Shop Type | B1: Listing Fee | C1: Transaction Fee | D1: Payment Fee
A2: Etsy | B2: 0.2 | C2: 5 | D2: 3
A3: Amazon Handmade | B3: 0.3 | C3: 6 | D3: 3
A4: Shopify | B4: 0 | C4: 2.9 | D4: 2.5
A6: TOTAL | B6: =SUM(B2:B4) | C6: =SUM(C2:C4) | D6: =SUM(D2:D4)

Sheet Payments
A1: Date | B1: Invoice | C1: Amount | D1: Status | E1: Due Date | F1: Balance | G1: Overdue?
A2: 46266 | B2: INV-1001 | C2: 120 | D2: Paid | E2: 46275 | F2: =N(C2)-0 | G2: =IF(AND(ISNUMBER(E2),D2<>"Paid",E2<TODAY()),"OVERDUE","")
A3: 46270 | B3: INV-1002 | C3: 85 | D3: Unpaid | E3: 46280 | F3: =N(F2)+N(C3)-0 | G3: =IF(AND(ISNUMBER(E3),D3<>"Paid",E3<TODAY()),"OVERDUE","")
A4: 46277 | B4: INV-1003 | C4: 200 | D4: Unpaid | E4: 46287 | F4: =N(F3)+N(C4)-0 | G4: =IF(AND(ISNUMBER(E4),D4<>"Paid",E4<TODAY()),"OVERDUE","")
A5: 46285 | B5: INV-1004 | C5: 150 | D5: Paid | E5: 46295 | F5: =N(F4)+N(C5)-0 | G5: =IF(AND(ISNUMBER(E5),D5<>"Paid",E5<TODAY()),"OVERDUE","")
A7: TOTAL | C7: =SUM(C2:C5)
A8: Overdue rows | B8: =COUNTIF(G2:G5,"OVERDUE")
