Workbook

Sheet Instructions
A1: Google Sheets Inventory & Order Tracker for Small Shops – 6‑Tab Dashboard
A3: 1. Open the file in Google Sheets and choose **File → Make a copy** to add it to your Drive.
A4: 2. Fill in the **Inventory** tab with your SKUs, product names, current quantities, reorder thresholds and unit prices.
A5: 3. Whenever you make a sale, add a row to the **Orders** tab, select the appropriate status, and the sheet will update remaining stock and alert you to any over‑orders.
A6: 4. Record supplier invoices in the **Payments** tab; the sheet will highlight any unpaid invoices past their due date.
A7: 5. Watch the **Dashboard** tab for an at‑a‑glance view of stock health, pending orders and overdue payments.
A9: Works in Microsoft Excel, Google Sheets (File > Import) and Apple Numbers.
A11: Blue header rows stay visible while you scroll. Totals sit under each table.
A12: This template helps you organise your own numbers. It is not financial, tax or legal advice.

Sheet Dashboard
A1: Summary | B1: Value
A2: Inventory: Current Qty | B2: ='Inventory'!C6
A3: Inventory: Reorder Qty | B3: ='Inventory'!D6
A4: Inventory: Unit Price | B4: ='Inventory'!E6
A5: Inventory: Total Value | B5: ='Inventory'!F6
A6: Orders: Qty Ordered | B6: ='Orders'!D6
A7: Orders: Remaining Stock | B7: ='Orders'!H6
A8: Orders: Overdue rows | B8: ='Orders'!B7
A9: Payments: Amount | B9: ='Payments'!D6
A10: Payments: Overdue rows | B10: ='Payments'!B7

Sheet Inventory
A1: SKU | B1: Product Name | C1: Current Qty | D1: Reorder Qty | E1: Unit Price | F1: Total Value | G1: Low‑Stock Flag
A2: SKU001 | B2: Handmade Necklace | C2: 25 | D2: 10 | E2: 15.99 | F2: 399.75
A3: SKU002 | B3: Ceramic Mug | C3: 8 | D3: 12 | E3: 9.5 | F3: 76 | G3: ⚠️
A4: SKU003 | B4: Leather Wallet | C4: 30 | D4: 5 | E4: 45 | F4: 1350
A6: TOTAL | C6: =SUM(C2:C4) | D6: =SUM(D2:D4) | E6: =SUM(E2:E4) | F6: =SUM(F2:F4)

Sheet Orders
A1: Order ID | B1: Order Date | C1: SKU | D1: Qty Ordered | E1: Customer Name | F1: Status | G1: Due Ship Date | H1: Remaining Stock | I1: Overdue?
A2: ORD1001 | B2: 46266 | C2: SKU001 | D2: 2 | E2: Alice Smith | F2: Pending | G2: 46270 | H2: 23 | I2: =IF(AND(ISNUMBER(G2),F2<>"Shipped",G2<TODAY()),"OVERDUE","")
A3: ORD1002 | B3: 46267 | C3: SKU002 | D3: 5 | E3: Bob Jones | F3: Shipped | G3: 46269 | H3: 3 | I3: =IF(AND(ISNUMBER(G3),F3<>"Shipped",G3<TODAY()),"OVERDUE","")
A4: ORD1003 | B4: 46268 | C4: SKU003 | D4: 1 | E4: Carol Lee | F4: Pending | G4: 46272 | H4: 29 | I4: =IF(AND(ISNUMBER(G4),F4<>"Shipped",G4<TODAY()),"OVERDUE","")
A6: TOTAL | D6: =SUM(D2:D4) | H6: =SUM(H2:H4)
A7: Overdue rows | B7: =COUNTIF(I2:I4,"OVERDUE")

Sheet Payments
A1: Payment ID | B1: Date | C1: Supplier | D1: Amount | E1: Due Date | F1: Status | G1: Balance | H1: Overdue?
A2: PAY2001 | B2: 46262 | C2: Supplier A | D2: 250 | E2: 46275 | F2: Unpaid | G2: =0-N(D2) | H2: =IF(AND(ISNUMBER(E2),F2<>"Paid",E2<TODAY()),"OVERDUE","")
A3: PAY2002 | B3: 46254 | C3: Supplier B | D3: 120 | E3: 46270 | F3: Paid | G3: =N(G2)+0-N(D3) | H3: =IF(AND(ISNUMBER(E3),F3<>"Paid",E3<TODAY()),"OVERDUE","")
A4: PAY2003 | B4: 46249 | C4: Supplier C | D4: 340 | E4: 46264 | F4: Paid | G4: =N(G3)+0-N(D4) | H4: =IF(AND(ISNUMBER(E4),F4<>"Paid",E4<TODAY()),"OVERDUE","")
A6: TOTAL | D6: =SUM(D2:D4)
A7: Overdue rows | B7: =COUNTIF(H2:H4,"OVERDUE")
