Workbook

Sheet Instructions
A1: Google Sheets Budget for Freelancers – Income & Expense Tracker
A3: 1. Open the file in Google Sheets and choose **File → Make a copy** – this creates your own editable version while preserving the original as a reference.
A4: 2. In the **Overview** tab set the month (e.g., 2026‑03) and type your desired savings goal.
A5: 3. Enter every payment in the **Income** tab and every cost in the **Expenses** tab, using the drop‑down lists for Source and Category.
A6: 4. Return to **Overview** to see real‑time totals, net cash flow, and the two charts updating automatically.
A7: 5. Use the **Summary** tab to export a PDF report or copy the charts for personal reviews or to share with an accountant.
A9: Works in Microsoft Excel, Google Sheets (File > Import) and Apple Numbers.
A11: Blue header rows stay visible while you scroll. Totals sit under each table.
A12: This template helps you organise your own numbers. It is not financial, tax or legal advice.

Sheet Dashboard
A1: Summary | B1: Value
A2: Income: Amount | B2: ='Income'!D7
A3: Income: Overdue rows | B3: ='Income'!B8
A4: Expenses: Amount | B4: ='Expenses'!D7
A5: Expenses: Overdue rows | B5: ='Expenses'!B8
A6: Savings Tracker: Target Amount | B6: ='Savings Tracker'!C6
A7: Savings Tracker: Current Balance | B7: ='Savings Tracker'!D6

Sheet Income
A1: Date | B1: Client | C1: Source | D1: Amount | E1: Status | F1: Due Date | G1: Balance | H1: Overdue?
A2: 46082 | B2: Acme Corp | C2: Direct Client | D2: 1200 | E2: Paid | G2: =N(D2)-0 | H2: =IF(AND(ISNUMBER(F2),E2<>"Paid",F2<TODAY()),"OVERDUE","")
A3: 46089 | B3: Upwork | C3: Platform | D3: 500 | E3: Unpaid | F3: 46101 | G3: =N(G2)+N(D3)-0 | H3: =IF(AND(ISNUMBER(F3),E3<>"Paid",F3<TODAY()),"OVERDUE","")
A4: 46096 | B4: Fiverr | C4: Platform | D4: 300 | E4: Paid | G4: =N(G3)+N(D4)-0 | H4: =IF(AND(ISNUMBER(F4),E4<>"Paid",F4<TODAY()),"OVERDUE","")
A5: 46103 | B5: DesignCo | C5: Direct Client | D5: 800 | E5: Unpaid | F5: 46113 | G5: =N(G4)+N(D5)-0 | H5: =IF(AND(ISNUMBER(F5),E5<>"Paid",F5<TODAY()),"OVERDUE","")
A7: TOTAL | D7: =SUM(D2:D5)
A8: Overdue rows | B8: =COUNTIF(H2:H5,"OVERDUE")

Sheet Expenses
A1: Date | B1: Vendor | C1: Category | D1: Amount | E1: Status | F1: Due Date | G1: Balance | H1: Overdue?
A2: 46086 | B2: Google Cloud | C2: Software | D2: 150 | E2: Paid | G2: =0-N(D2) | H2: =IF(AND(ISNUMBER(F2),E2<>"Paid",F2<TODAY()),"OVERDUE","")
A3: 46091 | B3: IRS | C3: Taxes | D3: 300 | E3: Unpaid | F3: 46127 | G3: =N(G2)+0-N(D3) | H3: =IF(AND(ISNUMBER(F3),E3<>"Paid",F3<TODAY()),"OVERDUE","")
A4: 46093 | B4: Coffee Shop | C4: Travel | D4: 25 | E4: Paid | G4: =N(G3)+0-N(D4) | H4: =IF(AND(ISNUMBER(F4),E4<>"Paid",F4<TODAY()),"OVERDUE","")
A5: 46099 | B5: Stationery Co | C5: Supplies | D5: 45 | E5: Unpaid | F5: 46111 | G5: =N(G4)+0-N(D5) | H5: =IF(AND(ISNUMBER(F5),E5<>"Paid",F5<TODAY()),"OVERDUE","")
A7: TOTAL | D7: =SUM(D2:D5)
A8: Overdue rows | B8: =COUNTIF(H2:H5,"OVERDUE")

Sheet Savings Tracker
A1: Date | B1: Goal | C1: Target Amount | D1: Current Balance
A2: 46082 | B2: Emergency Fund | C2: 5000 | D2: 1200
A3: 46082 | B3: Equipment Upgrade | C3: 2000 | D3: 800
A4: 46082 | B4: Tax Reserve | C4: 3000 | D4: 1500
A6: TOTAL | C6: =SUM(C2:C4) | D6: =SUM(D2:D4)
